{
  "aor": 0.0006149723756906077,
  "aqi": 0.006705122928176796,
  "bids_meta": {
    "RepetitionTime": 2.0,
    "TaskName": "selective stop-signal task",
    "dataset": "ds000017",
    "modality": "bold",
    "run_id": 1,
    "session_id": "timepoint1",
    "subject_id": "7",
    "task_id": "selectivestopsignaltask"
  },
  "dummy_trs": 1,
  "dvars_nstd": 27.47541425505556,
  "dvars_std": 1.0775913497222227,
  "dvars_vstd": 0.99600207,
  "efc": 0.5761333231147886,
  "fber": 1357.6546630859375,
  "fd_mean": 0.13081848544466546,
  "fd_num": 13,
  "fd_perc": 7.18232044198895,
  "fwhm_avg": 1.9285964,
  "fwhm_x": 1.8664447999999998,
  "fwhm_y": 2.1209344,
  "fwhm_z": 1.79841,
  "gcor": 0.0202486,
  "gsr_x": 0.004091945476830006,
  "gsr_y": 0.03877023234963417,
  "provenance": {
    "md5sum": "c6420549c12d45b750c2777c038deec1",
    "settings": {
      "fd_thres": 0.2,
      "testing": false
    },
    "software": "mriqc",
    "version": "22.0.1",
    "webapi_port": null,
    "webapi_url": "https://mriqc.nimh.nih.gov/api/v1"
  },
  "size_t": 181,
  "size_x": 64,
  "size_y": 64,
  "size_z": 33,
  "snr": 5.554623854314689,
  "spacing_tr": 2.0,
  "spacing_x": 3.125,
  "spacing_y": 3.125,
  "spacing_z": 4.0,
  "summary_bg_k": 19.702167270168804,
  "summary_bg_mad": 7.8225698882822225,
  "summary_bg_mean": 38.4891471862793,
  "summary_bg_median": 15.977901458740234,
  "summary_bg_n": 71865.0,
  "summary_bg_p05": 10.237569808959961,
  "summary_bg_p95": 145.66188964843752,
  "summary_bg_stdv": 59.30343246459961,
  "summary_fg_k": 1.019155179117739,
  "summary_fg_mad": 93.48995132644188,
  "summary_fg_mean": 606.7852783203125,
  "summary_fg_median": 605.737548828125,
  "summary_fg_n": 31090.0,
  "summary_fg_p05": 419.45693054199216,
  "summary_fg_p95": 784.5444976806641,
  "summary_fg_stdv": 109.0492935180664,
  "tsnr": 54.19869813148398
}