{
  "aor": 0.0005918232044198894,
  "aqi": 0.00860826502762431,
  "bids_meta": {
    "RepetitionTime": 2.0,
    "TaskName": "selective stop-signal task",
    "dataset": "ds000017",
    "modality": "bold",
    "run_id": 2,
    "session_id": "timepoint2",
    "subject_id": "6",
    "task_id": "selectivestopsignaltask"
  },
  "dummy_trs": 1,
  "dvars_nstd": 27.721581470000007,
  "dvars_std": 1.1347244861666665,
  "dvars_vstd": 1.0114723618888888,
  "efc": 0.5584401963169089,
  "fber": 1619.29052734375,
  "fd_mean": 0.047275746323493,
  "fd_num": 1,
  "fd_perc": 0.5524861878453039,
  "fwhm_avg": 1.6990187666666667,
  "fwhm_x": 1.6566176,
  "fwhm_y": 1.8942112,
  "fwhm_z": 1.5462275,
  "gcor": 0.0182189,
  "gsr_x": 0.0002375916374148801,
  "gsr_y": 0.04707321897149086,
  "provenance": {
    "md5sum": "fbcc178e3d9dd1d8a09e1831b8c37eea",
    "settings": {
      "fd_thres": 0.2,
      "testing": false
    },
    "software": "mriqc",
    "version": "22.0.1",
    "webapi_port": null,
    "webapi_url": "https://mriqc.nimh.nih.gov/api/v1"
  },
  "size_t": 181,
  "size_x": 64,
  "size_y": 64,
  "size_z": 33,
  "snr": 7.1031308516180145,
  "spacing_tr": 2.0,
  "spacing_x": 3.125,
  "spacing_y": 3.125,
  "spacing_z": 4.0,
  "summary_bg_k": 37.525011684164106,
  "summary_bg_mad": 5.8648807675078185,
  "summary_bg_mean": 33.042598724365234,
  "summary_bg_median": 13.767956733703613,
  "summary_bg_n": 75221.0,
  "summary_bg_p05": 9.4143648147583,
  "summary_bg_p95": 117.34254455566406,
  "summary_bg_stdv": 55.73200988769531,
  "summary_fg_k": 2.3566780970862826,
  "summary_fg_mad": 71.49664597392817,
  "summary_fg_mean": 576.0399780273438,
  "summary_fg_median": 570.8701782226562,
  "summary_fg_n": 28510.0,
  "summary_fg_p05": 460.4900726318359,
  "summary_fg_p95": 708.453646850586,
  "summary_fg_stdv": 80.36740112304688,
  "tsnr": 60.221956653054804
}